geotorchai/__init__.py
geotorchai/datasets/__init__.py
geotorchai/datasets/grid/__init__.py
geotorchai/datasets/grid/geopotential.py
geotorchai/datasets/grid/nyc_bike_deepstn.py
geotorchai/datasets/grid/nyc_bike_stdn.py
geotorchai/datasets/grid/nyc_taxi_stdn.py
geotorchai/datasets/grid/processed.py
geotorchai/datasets/grid/taxi_bj_21.py
geotorchai/datasets/grid/temperature.py
geotorchai/datasets/grid/toa_incident_solar_radiation.py
geotorchai/datasets/grid/total_cloud_cover.py
geotorchai/datasets/grid/total_precipitation.py
geotorchai/datasets/raster/__init__.py
geotorchai/datasets/raster/cloud_38.py
geotorchai/datasets/raster/euro_sat.py
geotorchai/datasets/raster/processed.py
geotorchai/datasets/raster/processed_extra_features.py
geotorchai/datasets/raster/sat4.py
geotorchai/datasets/raster/sat6.py
geotorchai/datasets/raster/slum_detection.py
geotorchai/datasets/raster/utility/__init__.py
geotorchai/datasets/raster/utility/spectral_indices.py
geotorchai/datasets/raster/utility/textural_features.py
geotorchai/models/__init__.py
geotorchai/models/grid/__init__.py
geotorchai/models/grid/conv_lstm.py
geotorchai/models/grid/deep_stn_net.py
geotorchai/models/grid/periodical_cnn.py
geotorchai/models/grid/st_resnet.py
geotorchai/models/raster/__init__.py
geotorchai/models/raster/deepsat2.py
geotorchai/models/raster/fcn.py
geotorchai/models/raster/sat_cnn.py
geotorchai/models/raster/unet.py
geotorchai/preprocessing/__init__.py
geotorchai/preprocessing/adapter.py
geotorchai/preprocessing/geo_io.py
geotorchai/preprocessing/spark_registration.py
geotorchai/preprocessing/enums/__init__.py
geotorchai/preprocessing/enums/adjacency_type.py
geotorchai/preprocessing/enums/aggregation_type.py
geotorchai/preprocessing/enums/geo_file_type.py
geotorchai/preprocessing/enums/geo_relationship.py
geotorchai/preprocessing/grid/__init__.py
geotorchai/preprocessing/grid/adjacency.py
geotorchai/preprocessing/grid/space_partition.py
geotorchai/preprocessing/grid/st_manager.py
geotorchai-0.2.0.dist-info/LICENSE.md
geotorchai-0.2.0.dist-info/METADATA
geotorchai-0.2.0.dist-info/WHEEL
geotorchai-0.2.0.dist-info/top_level.txt
geotorchai-0.2.0.dist-info/RECORD
