Metadata-Version: 2.1
Name: geotorchai
Version: 0.2.0
Summary: GeoTorchAI, formarly GeoTorch, A Spatiotemporal Deep Learning Framework
Home-page: https://github.com/DataSystemsLab/GeoTorch
Author: Kanchan Chowdhury
Author-email: kchowdh1@asu.edu
License: AGPL-3.0
Keywords: spatial-machine-learning,spatiotemporal-deep-learning,spatial forecasting,deep learning,machine learning,spatiotemporal forecasting,temporal signal,raster classification,satellite classification,raster segmentation,satellite segmentation,convlstm,st-resnet,deepstn+,deepsatv2,lstm,temporal network,eurosat,representation learning
Classifier: Development Status :: 3 - Alpha
Classifier: Intended Audience :: Developers
Classifier: Intended Audience :: Science/Research
Classifier: Topic :: Software Development :: Build Tools
Classifier: Topic :: Scientific/Engineering :: Artificial Intelligence
Classifier: Topic :: Scientific/Engineering :: GIS
Classifier: Operating System :: OS Independent
Classifier: Programming Language :: Python :: 3.6
Requires-Python: >=3.6
License-File: LICENSE.md
Requires-Dist: torch
Requires-Dist: rasterio (<=1.1.8)
Requires-Dist: scikit-image (>=0.19.0)
Requires-Dist: numpy
Requires-Dist: pandas
Requires-Dist: xarray
Requires-Dist: cdsapi
Provides-Extra: preprocessing
Requires-Dist: pyspark ; extra == 'preprocessing'
Requires-Dist: apache-sedona ; extra == 'preprocessing'
